boston_housing_prediction/__init__.py
boston_housing_prediction/__main__.py
boston_housing_prediction/boston_main.py
boston_housing_prediction/linear_regression_model.py
boston_housing_prediction/misc_libary.py
boston_housing_prediction/normal_equation_model.py
boston_housing_prediction/polynomial_regression_model.py
boston_housing_prediction/visualize_libary.py
boston_housing_prediction-0.3.0.data/scripts/__main__.py
boston_housing_prediction-0.3.0.dist-info/LICENSE
boston_housing_prediction-0.3.0.dist-info/METADATA
boston_housing_prediction-0.3.0.dist-info/WHEEL
boston_housing_prediction-0.3.0.dist-info/entry_points.txt
boston_housing_prediction-0.3.0.dist-info/top_level.txt
boston_housing_prediction-0.3.0.dist-info/RECORD
