Metadata-Version: 2.1
Name: boston-housing-prediction
Version: 0.3.0
Summary: Predict housing prices in boston.
Home-page: https://github.com/LuposX/BostonHousingPrediction
Author: Lupos
Author-email: buisnessgithublupos@gmail.com
License: MIT
Keywords: regression meachine-learning housing_prices_boston learning_purpose
Platform: UNKNOWN
Classifier: License :: OSI Approved :: MIT License
Classifier: Operating System :: OS Independent
Classifier: Programming Language :: Python :: 3.5
Classifier: Programming Language :: Python :: 3.6
Classifier: Programming Language :: Python :: 3.7
Requires-Python: >=3.5
Requires-Dist: certifi
Requires-Dist: cycler
Requires-Dist: kiwisolver
Requires-Dist: matplotlib
Requires-Dist: numpy
Requires-Dist: pandas
Requires-Dist: pyparsing
Requires-Dist: python-dateutil
Requires-Dist: pytz
Requires-Dist: scipy
Requires-Dist: seaborn
Requires-Dist: six
Requires-Dist: wincertstore
